moveread/tnmt/__init__.py
moveread/tnmt/__init__.pyi
moveread/tnmt/_types.py
moveread/tnmt/admin/__init__.py
moveread/tnmt/admin/__init__.pyi
moveread/tnmt/admin/admin.py
moveread/tnmt/jobs/__init__.py
moveread/tnmt/jobs/__init__.pyi
moveread/tnmt/jobs/cli.py
moveread/tnmt/jobs/pairings.py
moveread/tnmt/queries/__init__.py
moveread/tnmt/queries/__init__.pyi
moveread/tnmt/queries/api.py
moveread/tnmt/queries/basic.py
moveread/tnmt/queries/pairings.py
moveread/tnmt/server/__init__.py
moveread/tnmt/server/__init__.pyi
moveread/tnmt/server/api.py
moveread/tnmt/server/cli.py
moveread/tnmt/server/clientgen_cli.py
moveread/tnmt/server/main.py
moveread/tnmt/server/pgns.py
moveread/tnmt/server/sdk.py
moveread/tnmt/server/util.py
moveread_tnmt-0.2.8.dist-info/METADATA
moveread_tnmt-0.2.8.dist-info/WHEEL
moveread_tnmt-0.2.8.dist-info/entry_points.txt
moveread_tnmt-0.2.8.dist-info/top_level.txt
moveread_tnmt-0.2.8.dist-info/RECORD
