Metadata-Version: 2.1
Name: moveread-tnmt
Version: 0.2.8
Summary: Moveread for Tournaments, the API
Author-email: Marcel Claramunt <marcel@moveread.com>
Project-URL: repo, https://github.com/moveread/tnmt.git
Requires-Python: >=3.10
Requires-Dist: lazy-loader
Requires-Dist: sqlmodel
Requires-Dist: sqltypes
Requires-Dist: python-kv
Requires-Dist: pure-cv
Requires-Dist: chess-pairings
Requires-Dist: chess-scraping
Requires-Dist: chess-utils
Provides-Extra: cli
Requires-Dist: typer; extra == "cli"
Provides-Extra: server
Requires-Dist: fastapi; extra == "server"
Requires-Dist: aiohttp; extra == "server"
Requires-Dist: python-kv[blob]; extra == "server"
Requires-Dist: python-multipart; extra == "server"
